README.rst
que.py
setup.py
que.egg-info/PKG-INFO
que.egg-info/SOURCES.txt
que.egg-info/dependency_links.txt
que.egg-info/entry_points.txt
que.egg-info/requires.txt
que.egg-info/top_level.txt